odoo/addons/stock_picking_purchase_order_link/README.rst
odoo/addons/stock_picking_purchase_order_link/__init__.py
odoo/addons/stock_picking_purchase_order_link/__manifest__.py
odoo/addons/stock_picking_purchase_order_link/i18n/stock_picking_purchase_order_link.pot
odoo/addons/stock_picking_purchase_order_link/models/__init__.py
odoo/addons/stock_picking_purchase_order_link/models/stock_picking.py
odoo/addons/stock_picking_purchase_order_link/readme/CONTRIBUTORS.rst
odoo/addons/stock_picking_purchase_order_link/readme/DESCRIPTION.rst
odoo/addons/stock_picking_purchase_order_link/readme/USAGE.rst
odoo/addons/stock_picking_purchase_order_link/static/description/icon.png
odoo/addons/stock_picking_purchase_order_link/static/description/index.html
odoo/addons/stock_picking_purchase_order_link/tests/__init__.py
odoo/addons/stock_picking_purchase_order_link/tests/test_stock_picking_purchase_order_link.py
odoo/addons/stock_picking_purchase_order_link/views/stock_picking_view.xml
odoo11_addon_stock_picking_purchase_order_link-11.0.1.0.0.99.dev3.dist-info/METADATA
odoo11_addon_stock_picking_purchase_order_link-11.0.1.0.0.99.dev3.dist-info/WHEEL
odoo11_addon_stock_picking_purchase_order_link-11.0.1.0.0.99.dev3.dist-info/top_level.txt
odoo11_addon_stock_picking_purchase_order_link-11.0.1.0.0.99.dev3.dist-info/RECORD
